mtclient
tests
