Metadata-Version: 2.1
Name: mytardisclient
Version: 0.3.4
Summary: Command Line Interface and Python classes for interacting with MyTardis's REST API.
Home-page: http://github.com/mytardis/mytardisclient
Author: James Wettenhall
Author-email: james.wettenhall@monash.edu
License: GPL
Download-URL: https://github.com/mytardis/mytardisclient/archive/0.3.4.tar.gz
Keywords: mytardis,REST
Platform: UNKNOWN
